Workbook

Sheet Инструкция
A1: Как работать с шаблоном бюджета закупок
A2: Татьяна Бандюк · tatsianabandziuk.com
A4: До сезона
A5: 1. План продаж | B5: Внесите план продаж по месяцам для каждого рынка и категории на листе OTB. Отправная точка — продажи тех же недель прошлого сезона.
A6: 2. План остатков и уценки | B6: Внесите план уценки и остаток, который нужен на конец каждого месяца. Остаток на начало вносится только для первого месяца, дальше его считает формула.
A7: 3. Бюджет | B7: Внесите уже размещённые заказы, маржинальность закупки и среднюю себестоимость единицы. Лист покажет open-to-buy в рознице, по себестоимости и в штуках.
A8: 4. Заказы | B8: Разложите штуки по размерам и цветам на листе «Размеры и цвета», разместите заказы и добавьте их в строку «Заказано».
A9: В течение сезона
A10: 5. Сверка с фактом | B10: Когда месяц закрыт, внесите фактические продажи и поставки и увеличьте номер текущего месяца. Перед следующим заказом откройте лист «Проверки».
A11: 6. Новый прогноз | B11: Если продажи ушли от плана, сначала измените план продаж и уценки на оставшиеся месяцы, потом снова смотрите на open-to-buy.
A12: Передача модели команде
A13: Владельцы | B13: У каждого показателя есть владелец на листе «Определения». Согласуйте имена до начала сезона.
A14: Изменения | B14: Новый рынок или категория: скопируйте полный блок из 13 строк под последним и поменяйте названия. Блок «Все рынки» учтёт его автоматически.
A15: Обозначения | B15: Жёлтая ячейка — ввод. Белая — формула. Зелёный заголовок — раздел. Значения в примере условные, замените их своими.

Sheet OTB
A1: Бюджет закупок open-to-buy по месяцам, категориям и рынкам
A2: Жёлтые ячейки — ввод данных. Белые — формулы, их не перезаписывайте. Все суммы в розничных ценах, если в строке не сказано о себестоимости или штуках.
A4: Сезон | C4: ВЛ27
A5: Валюта | C5: EUR
A6: Текущий месяц (1–6) | C6: 2
A7: Допустимое отклонение | C7: 0.1
C10: Месяцы | D10: 1 | E10: 2 | F10: 3 | G10: 4 | H10: 5 | I10: 6
A11: Рынок | B11: Категория | C11: Строка | D11: фев | E11: мар | F11: апр | G11: май | H11: июн | I11: июл | J11: Итого за сезон
A13: Все рынки | B13: Все категории | C13: План продаж | D13: =SUMIF($C$26:$C$400,$C13,D$26:D$400) | E13: =SUMIF($C$26:$C$400,$C13,E$26:E$400) | F13: =SUMIF($C$26:$C$400,$C13,F$26:F$400) | G13: =SUMIF($C$26:$C$400,$C13,G$26:G$400) | H13: =SUMIF($C$26:$C$400,$C13,H$26:H$400) | I13: =SUMIF($C$26:$C$400,$C13,I$26:I$400) | J13: =SUM(D13:I13)
C14: План уценки | D14: =SUMIF($C$26:$C$400,$C14,D$26:D$400) | E14: =SUMIF($C$26:$C$400,$C14,E$26:E$400) | F14: =SUMIF($C$26:$C$400,$C14,F$26:F$400) | G14: =SUMIF($C$26:$C$400,$C14,G$26:G$400) | H14: =SUMIF($C$26:$C$400,$C14,H$26:H$400) | I14: =SUMIF($C$26:$C$400,$C14,I$26:I$400) | J14: =SUM(D14:I14)
C15: План остатка на конец | D15: =SUMIF($C$26:$C$400,$C15,D$26:D$400) | E15: =SUMIF($C$26:$C$400,$C15,E$26:E$400) | F15: =SUMIF($C$26:$C$400,$C15,F$26:F$400) | G15: =SUMIF($C$26:$C$400,$C15,G$26:G$400) | H15: =SUMIF($C$26:$C$400,$C15,H$26:H$400) | I15: =SUMIF($C$26:$C$400,$C15,I$26:I$400) | J15: =I15
C16: Остаток на начало | D16: =SUMIF($C$26:$C$400,$C16,D$26:D$400) | E16: =SUMIF($C$26:$C$400,$C16,E$26:E$400) | F16: =SUMIF($C$26:$C$400,$C16,F$26:F$400) | G16: =SUMIF($C$26:$C$400,$C16,G$26:G$400) | H16: =SUMIF($C$26:$C$400,$C16,H$26:H$400) | I16: =SUMIF($C$26:$C$400,$C16,I$26:I$400) | J16: =D16
C17: Заказано | D17: =SUMIF($C$26:$C$400,$C17,D$26:D$400) | E17: =SUMIF($C$26:$C$400,$C17,E$26:E$400) | F17: =SUMIF($C$26:$C$400,$C17,F$26:F$400) | G17: =SUMIF($C$26:$C$400,$C17,G$26:G$400) | H17: =SUMIF($C$26:$C$400,$C17,H$26:H$400) | I17: =SUMIF($C$26:$C$400,$C17,I$26:I$400) | J17: =SUM(D17:I17)
C18: Open-to-buy | D18: =SUMIF($C$26:$C$400,$C18,D$26:D$400) | E18: =SUMIF($C$26:$C$400,$C18,E$26:E$400) | F18: =SUMIF($C$26:$C$400,$C18,F$26:F$400) | G18: =SUMIF($C$26:$C$400,$C18,G$26:G$400) | H18: =SUMIF($C$26:$C$400,$C18,H$26:H$400) | I18: =SUMIF($C$26:$C$400,$C18,I$26:I$400) | J18: =SUM(D18:I18)
C19: Маржинальность закупки % | D19: =IF(D18=0,"",1-D20/D18) | E19: =IF(E18=0,"",1-E20/E18) | F19: =IF(F18=0,"",1-F20/F18) | G19: =IF(G18=0,"",1-G20/G18) | H19: =IF(H18=0,"",1-H20/H18) | I19: =IF(I18=0,"",1-I20/I18) | J19: =IF(J18=0,"",1-J20/J18)
C20: Open-to-buy по себестоимости | D20: =SUMIF($C$26:$C$400,$C20,D$26:D$400) | E20: =SUMIF($C$26:$C$400,$C20,E$26:E$400) | F20: =SUMIF($C$26:$C$400,$C20,F$26:F$400) | G20: =SUMIF($C$26:$C$400,$C20,G$26:G$400) | H20: =SUMIF($C$26:$C$400,$C20,H$26:H$400) | I20: =SUMIF($C$26:$C$400,$C20,I$26:I$400) | J20: =SUM(D20:I20)
C21: Средняя себестоимость единицы | D21: =IF(D22=0,"",D20/D22) | E21: =IF(E22=0,"",E20/E22) | F21: =IF(F22=0,"",F20/F22) | G21: =IF(G22=0,"",G20/G22) | H21: =IF(H22=0,"",H20/H22) | I21: =IF(I22=0,"",I20/I22)
C22: Open-to-buy в штуках | D22: =SUMIF($C$26:$C$400,$C22,D$26:D$400) | E22: =SUMIF($C$26:$C$400,$C22,E$26:E$400) | F22: =SUMIF($C$26:$C$400,$C22,F$26:F$400) | G22: =SUMIF($C$26:$C$400,$C22,G$26:G$400) | H22: =SUMIF($C$26:$C$400,$C22,H$26:H$400) | I22: =SUMIF($C$26:$C$400,$C22,I$26:I$400) | J22: =SUM(D22:I22)
C23: Продажи факт | D23: =SUMIF($C$26:$C$400,$C23,D$26:D$400) | E23: =SUMIF($C$26:$C$400,$C23,E$26:E$400) | F23: =SUMIF($C$26:$C$400,$C23,F$26:F$400) | G23: =SUMIF($C$26:$C$400,$C23,G$26:G$400) | H23: =SUMIF($C$26:$C$400,$C23,H$26:H$400) | I23: =SUMIF($C$26:$C$400,$C23,I$26:I$400) | J23: =SUM(D23:I23)
C24: Поставки факт | D24: =SUMIF($C$26:$C$400,$C24,D$26:D$400) | E24: =SUMIF($C$26:$C$400,$C24,E$26:E$400) | F24: =SUMIF($C$26:$C$400,$C24,F$26:F$400) | G24: =SUMIF($C$26:$C$400,$C24,G$26:G$400) | H24: =SUMIF($C$26:$C$400,$C24,H$26:H$400) | I24: =SUMIF($C$26:$C$400,$C24,I$26:I$400) | J24: =SUM(D24:I24)
C25: Проверка | D25: =IF(COUNTIF(D$26:D$400,"Перезакуп")>0,"Перезакуп",IF(COUNTIF(D$26:D$400,"Внесите факт")>0,"Внесите факт",IF(COUNTIF(D$26:D$400,"Продажи вне плана")>0,"Продажи вне плана",IF(D$10>$C$6,"","OK")))) | E25: =IF(COUNTIF(E$26:E$400,"Перезакуп")>0,"Перезакуп",IF(COUNTIF(E$26:E$400,"Внесите факт")>0,"Внесите факт",IF(COUNTIF(E$26:E$400,"Продажи вне плана")>0,"Продажи вне плана",IF(E$10>$C$6,"","OK")))) | F25: =IF(COUNTIF(F$26:F$400,"Перезакуп")>0,"Перезакуп",IF(COUNTIF(F$26:F$400,"Внесите факт")>0,"Внесите факт",IF(COUNTIF(F$26:F$400,"Продажи вне плана")>0,"Продажи вне плана",IF(F$10>$C$6,"","OK")))) | G25: =IF(COUNTIF(G$26:G$400,"Перезакуп")>0,"Перезакуп",IF(COUNTIF(G$26:G$400,"Внесите факт")>0,"Внесите факт",IF(COUNTIF(G$26:G$400,"Продажи вне плана")>0,"Продажи вне плана",IF(G$10>$C$6,"","OK")))) | H25: =IF(COUNTIF(H$26:H$400,"Перезакуп")>0,"Перезакуп",IF(COUNTIF(H$26:H$400,"Внесите факт")>0,"Внесите факт",IF(COUNTIF(H$26:H$400,"Продажи вне плана")>0,"Продажи вне плана",IF(H$10>$C$6,"","OK")))) | I25: =IF(COUNTIF(I$26:I$400,"Перезакуп")>0,"Перезакуп",IF(COUNTIF(I$26:I$400,"Внесите факт")>0,"Внесите факт",IF(COUNTIF(I$26:I$400,"Продажи вне плана")>0,"Продажи вне плана",IF(I$10>$C$6,"","OK"))))
A26: Рынок A | B26: Платья | C26: План продаж | D26: 42000 | E26: 48000 | F26: 55000 | G26: 60000 | H26: 52000 | I26: 38000 | J26: =SUM(D26:I26)
C27: План уценки | D27: 1500 | E27: 1800 | F27: 2500 | G27: 4000 | H27: 9000 | I27: 12000 | J27: =SUM(D27:I27)
C28: План остатка на конец | D28: 120000 | E28: 130000 | F28: 125000 | G28: 110000 | H28: 80000 | I28: 50000 | J28: =I28
C29: Остаток на начало | D29: 110000 | E29: =D28 | F29: =E28 | G29: =F28 | H29: =G28 | I29: =H28 | J29: =D29
C30: Заказано | D30: 30000 | E30: 40000 | F30: 35000 | G30: 20000 | H30: 10000 | I30: 0 | J30: =SUM(D30:I30)
C31: Open-to-buy | D31: =D26+D27+D28-D29-D30 | E31: =E26+E27+E28-E29-E30 | F31: =F26+F27+F28-F29-F30 | G31: =G26+G27+G28-G29-G30 | H31: =H26+H27+H28-H29-H30 | I31: =I26+I27+I28-I29-I30 | J31: =SUM(D31:I31)
C32: Маржинальность закупки % | D32: 0.62 | E32: =D32 | F32: =E32 | G32: =F32 | H32: =G32 | I32: =H32 | J32: =IF(J31=0,"",1-J33/J31)
C33: Open-to-buy по себестоимости | D33: =D31*(1-D32) | E33: =E31*(1-E32) | F33: =F31*(1-F32) | G33: =G31*(1-G32) | H33: =H31*(1-H32) | I33: =I31*(1-I32) | J33: =SUM(D33:I33)
C34: Средняя себестоимость единицы | D34: 24 | E34: =D34 | F34: =E34 | G34: =F34 | H34: =G34 | I34: =H34
C35: Open-to-buy в штуках | D35: =IF(D34>0,ROUND(D33/D34,0),0) | E35: =IF(E34>0,ROUND(E33/E34,0),0) | F35: =IF(F34>0,ROUND(F33/F34,0),0) | G35: =IF(G34>0,ROUND(G33/G34,0),0) | H35: =IF(H34>0,ROUND(H33/H34,0),0) | I35: =IF(I34>0,ROUND(I33/I34,0),0) | J35: =SUM(D35:I35)
C36: Продажи факт | D36: 40500 | E36: 51000 | J36: =SUM(D36:I36)
C37: Поставки факт | D37: 29000 | E37: 41500 | J37: =SUM(D37:I37)
C38: Проверка | D38: =IF(D31<0,"Перезакуп",IF(D$10>$C$6,"",IF(OR(D36="",D37=""),"Внесите факт",IF(AND(D26>0,ABS(D36/D26-1)>$C$7),"Продажи вне плана","OK")))) | E38: =IF(E31<0,"Перезакуп",IF(E$10>$C$6,"",IF(OR(E36="",E37=""),"Внесите факт",IF(AND(E26>0,ABS(E36/E26-1)>$C$7),"Продажи вне плана","OK")))) | F38: =IF(F31<0,"Перезакуп",IF(F$10>$C$6,"",IF(OR(F36="",F37=""),"Внесите факт",IF(AND(F26>0,ABS(F36/F26-1)>$C$7),"Продажи вне плана","OK")))) | G38: =IF(G31<0,"Перезакуп",IF(G$10>$C$6,"",IF(OR(G36="",G37=""),"Внесите факт",IF(AND(G26>0,ABS(G36/G26-1)>$C$7),"Продажи вне плана","OK")))) | H38: =IF(H31<0,"Перезакуп",IF(H$10>$C$6,"",IF(OR(H36="",H37=""),"Внесите факт",IF(AND(H26>0,ABS(H36/H26-1)>$C$7),"Продажи вне плана","OK")))) | I38: =IF(I31<0,"Перезакуп",IF(I$10>$C$6,"",IF(OR(I36="",I37=""),"Внесите факт",IF(AND(I26>0,ABS(I36/I26-1)>$C$7),"Продажи вне плана","OK"))))
A39: Рынок A | B39: Трикотаж | C39: План продаж | D39: 26000 | E39: 24000 | F39: 18000 | G39: 12000 | H39: 9000 | I39: 7000 | J39: =SUM(D39:I39)
C40: План уценки | D40: 1000 | E40: 1500 | F40: 2500 | G40: 3500 | H40: 3000 | I40: 2500 | J40: =SUM(D40:I40)
C41: План остатка на конец | D41: 70000 | E41: 60000 | F41: 45000 | G41: 30000 | H41: 20000 | I41: 12000 | J41: =I41
C42: Остаток на начало | D42: 75000 | E42: =D41 | F42: =E41 | G42: =F41 | H42: =G41 | I42: =H41 | J42: =D42
C43: Заказано | D43: 15000 | E43: 8000 | F43: 5000 | G43: 0 | H43: 0 | I43: 0 | J43: =SUM(D43:I43)
C44: Open-to-buy | D44: =D39+D40+D41-D42-D43 | E44: =E39+E40+E41-E42-E43 | F44: =F39+F40+F41-F42-F43 | G44: =G39+G40+G41-G42-G43 | H44: =H39+H40+H41-H42-H43 | I44: =I39+I40+I41-I42-I43 | J44: =SUM(D44:I44)
C45: Маржинальность закупки % | D45: 0.6 | E45: =D45 | F45: =E45 | G45: =F45 | H45: =G45 | I45: =H45 | J45: =IF(J44=0,"",1-J46/J44)
C46: Open-to-buy по себестоимости | D46: =D44*(1-D45) | E46: =E44*(1-E45) | F46: =F44*(1-F45) | G46: =G44*(1-G45) | H46: =H44*(1-H45) | I46: =I44*(1-I45) | J46: =SUM(D46:I46)
C47: Средняя себестоимость единицы | D47: 19 | E47: =D47 | F47: =E47 | G47: =F47 | H47: =G47 | I47: =H47
C48: Open-to-buy в штуках | D48: =IF(D47>0,ROUND(D46/D47,0),0) | E48: =IF(E47>0,ROUND(E46/E47,0),0) | F48: =IF(F47>0,ROUND(F46/F47,0),0) | G48: =IF(G47>0,ROUND(G46/G47,0),0) | H48: =IF(H47>0,ROUND(H46/H47,0),0) | I48: =IF(I47>0,ROUND(I46/I47,0),0) | J48: =SUM(D48:I48)
C49: Продажи факт | D49: 27200 | E49: 21000 | J49: =SUM(D49:I49)
C50: Поставки факт | D50: 15000 | E50: 8000 | J50: =SUM(D50:I50)
C51: Проверка | D51: =IF(D44<0,"Перезакуп",IF(D$10>$C$6,"",IF(OR(D49="",D50=""),"Внесите факт",IF(AND(D39>0,ABS(D49/D39-1)>$C$7),"Продажи вне плана","OK")))) | E51: =IF(E44<0,"Перезакуп",IF(E$10>$C$6,"",IF(OR(E49="",E50=""),"Внесите факт",IF(AND(E39>0,ABS(E49/E39-1)>$C$7),"Продажи вне плана","OK")))) | F51: =IF(F44<0,"Перезакуп",IF(F$10>$C$6,"",IF(OR(F49="",F50=""),"Внесите факт",IF(AND(F39>0,ABS(F49/F39-1)>$C$7),"Продажи вне плана","OK")))) | G51: =IF(G44<0,"Перезакуп",IF(G$10>$C$6,"",IF(OR(G49="",G50=""),"Внесите факт",IF(AND(G39>0,ABS(G49/G39-1)>$C$7),"Продажи вне плана","OK")))) | H51: =IF(H44<0,"Перезакуп",IF(H$10>$C$6,"",IF(OR(H49="",H50=""),"Внесите факт",IF(AND(H39>0,ABS(H49/H39-1)>$C$7),"Продажи вне плана","OK")))) | I51: =IF(I44<0,"Перезакуп",IF(I$10>$C$6,"",IF(OR(I49="",I50=""),"Внесите факт",IF(AND(I39>0,ABS(I49/I39-1)>$C$7),"Продажи вне плана","OK"))))
A52: Рынок B | B52: Платья | C52: План продаж | D52: 18000 | E52: 21000 | F52: 24000 | G52: 26000 | H52: 22000 | I52: 16000 | J52: =SUM(D52:I52)
C53: План уценки | D53: 600 | E53: 800 | F53: 1100 | G53: 1800 | H53: 4000 | I53: 5500 | J53: =SUM(D53:I53)
C54: План остатка на конец | D54: 52000 | E54: 56000 | F54: 54000 | G54: 47000 | H54: 35000 | I54: 22000 | J54: =I54
C55: Остаток на начало | D55: 48000 | E55: =D54 | F55: =E54 | G55: =F54 | H55: =G54 | I55: =H54 | J55: =D55
C56: Заказано | D56: 14000 | E56: 18000 | F56: 15000 | G56: 9000 | H56: 4000 | I56: 0 | J56: =SUM(D56:I56)
C57: Open-to-buy | D57: =D52+D53+D54-D55-D56 | E57: =E52+E53+E54-E55-E56 | F57: =F52+F53+F54-F55-F56 | G57: =G52+G53+G54-G55-G56 | H57: =H52+H53+H54-H55-H56 | I57: =I52+I53+I54-I55-I56 | J57: =SUM(D57:I57)
C58: Маржинальность закупки % | D58: 0.62 | E58: =D58 | F58: =E58 | G58: =F58 | H58: =G58 | I58: =H58 | J58: =IF(J57=0,"",1-J59/J57)
C59: Open-to-buy по себестоимости | D59: =D57*(1-D58) | E59: =E57*(1-E58) | F59: =F57*(1-F58) | G59: =G57*(1-G58) | H59: =H57*(1-H58) | I59: =I57*(1-I58) | J59: =SUM(D59:I59)
C60: Средняя себестоимость единицы | D60: 24 | E60: =D60 | F60: =E60 | G60: =F60 | H60: =G60 | I60: =H60
C61: Open-to-buy в штуках | D61: =IF(D60>0,ROUND(D59/D60,0),0) | E61: =IF(E60>0,ROUND(E59/E60,0),0) | F61: =IF(F60>0,ROUND(F59/F60,0),0) | G61: =IF(G60>0,ROUND(G59/G60,0),0) | H61: =IF(H60>0,ROUND(H59/H60,0),0) | I61: =IF(I60>0,ROUND(I59/I60,0),0) | J61: =SUM(D61:I61)
C62: Продажи факт | D62: 16100 | E62: 19800 | J62: =SUM(D62:I62)
C63: Поставки факт | D63: 14000 | J63: =SUM(D63:I63)
C64: Проверка | D64: =IF(D57<0,"Перезакуп",IF(D$10>$C$6,"",IF(OR(D62="",D63=""),"Внесите факт",IF(AND(D52>0,ABS(D62/D52-1)>$C$7),"Продажи вне плана","OK")))) | E64: =IF(E57<0,"Перезакуп",IF(E$10>$C$6,"",IF(OR(E62="",E63=""),"Внесите факт",IF(AND(E52>0,ABS(E62/E52-1)>$C$7),"Продажи вне плана","OK")))) | F64: =IF(F57<0,"Перезакуп",IF(F$10>$C$6,"",IF(OR(F62="",F63=""),"Внесите факт",IF(AND(F52>0,ABS(F62/F52-1)>$C$7),"Продажи вне плана","OK")))) | G64: =IF(G57<0,"Перезакуп",IF(G$10>$C$6,"",IF(OR(G62="",G63=""),"Внесите факт",IF(AND(G52>0,ABS(G62/G52-1)>$C$7),"Продажи вне плана","OK")))) | H64: =IF(H57<0,"Перезакуп",IF(H$10>$C$6,"",IF(OR(H62="",H63=""),"Внесите факт",IF(AND(H52>0,ABS(H62/H52-1)>$C$7),"Продажи вне плана","OK")))) | I64: =IF(I57<0,"Перезакуп",IF(I$10>$C$6,"",IF(OR(I62="",I63=""),"Внесите факт",IF(AND(I52>0,ABS(I62/I52-1)>$C$7),"Продажи вне плана","OK"))))
A65: Рынок B | B65: Трикотаж | C65: План продаж | D65: 11000 | E65: 10000 | F65: 7500 | G65: 5000 | H65: 3800 | I65: 3000 | J65: =SUM(D65:I65)
C66: План уценки | D66: 400 | E66: 650 | F66: 1100 | G66: 1500 | H66: 1300 | I66: 1100 | J66: =SUM(D66:I66)
C67: План остатка на конец | D67: 30000 | E67: 26000 | F67: 19000 | G67: 13000 | H67: 8500 | I67: 5000 | J67: =I67
C68: Остаток на начало | D68: 32000 | E68: =D67 | F68: =E67 | G68: =F67 | H68: =G67 | I68: =H67 | J68: =D68
C69: Заказано | D69: 6000 | E69: 3500 | F69: 2000 | G69: 0 | H69: 0 | I69: 0 | J69: =SUM(D69:I69)
C70: Open-to-buy | D70: =D65+D66+D67-D68-D69 | E70: =E65+E66+E67-E68-E69 | F70: =F65+F66+F67-F68-F69 | G70: =G65+G66+G67-G68-G69 | H70: =H65+H66+H67-H68-H69 | I70: =I65+I66+I67-I68-I69 | J70: =SUM(D70:I70)
C71: Маржинальность закупки % | D71: 0.6 | E71: =D71 | F71: =E71 | G71: =F71 | H71: =G71 | I71: =H71 | J71: =IF(J70=0,"",1-J72/J70)
C72: Open-to-buy по себестоимости | D72: =D70*(1-D71) | E72: =E70*(1-E71) | F72: =F70*(1-F71) | G72: =G70*(1-G71) | H72: =H70*(1-H71) | I72: =I70*(1-I71) | J72: =SUM(D72:I72)
C73: Средняя себестоимость единицы | D73: 19 | E73: =D73 | F73: =E73 | G73: =F73 | H73: =G73 | I73: =H73
C74: Open-to-buy в штуках | D74: =IF(D73>0,ROUND(D72/D73,0),0) | E74: =IF(E73>0,ROUND(E72/E73,0),0) | F74: =IF(F73>0,ROUND(F72/F73,0),0) | G74: =IF(G73>0,ROUND(G72/G73,0),0) | H74: =IF(H73>0,ROUND(H72/H73,0),0) | I74: =IF(I73>0,ROUND(I72/I73,0),0) | J74: =SUM(D74:I74)
C75: Продажи факт | D75: 11300 | E75: 10400 | J75: =SUM(D75:I75)
C76: Поставки факт | D76: 6000 | E76: 3500 | J76: =SUM(D76:I76)
C77: Проверка | D77: =IF(D70<0,"Перезакуп",IF(D$10>$C$6,"",IF(OR(D75="",D76=""),"Внесите факт",IF(AND(D65>0,ABS(D75/D65-1)>$C$7),"Продажи вне плана","OK")))) | E77: =IF(E70<0,"Перезакуп",IF(E$10>$C$6,"",IF(OR(E75="",E76=""),"Внесите факт",IF(AND(E65>0,ABS(E75/E65-1)>$C$7),"Продажи вне плана","OK")))) | F77: =IF(F70<0,"Перезакуп",IF(F$10>$C$6,"",IF(OR(F75="",F76=""),"Внесите факт",IF(AND(F65>0,ABS(F75/F65-1)>$C$7),"Продажи вне плана","OK")))) | G77: =IF(G70<0,"Перезакуп",IF(G$10>$C$6,"",IF(OR(G75="",G76=""),"Внесите факт",IF(AND(G65>0,ABS(G75/G65-1)>$C$7),"Продажи вне плана","OK")))) | H77: =IF(H70<0,"Перезакуп",IF(H$10>$C$6,"",IF(OR(H75="",H76=""),"Внесите факт",IF(AND(H65>0,ABS(H75/H65-1)>$C$7),"Продажи вне плана","OK")))) | I77: =IF(I70<0,"Перезакуп",IF(I$10>$C$6,"",IF(OR(I75="",I76=""),"Внесите факт",IF(AND(I65>0,ABS(I75/I65-1)>$C$7),"Продажи вне плана","OK"))))

Sheet Проверки
A1: Три проверки, которые не дают бюджету разойтись с фактом
A2: Число отмеченных месяцев по каждому блоку. Всё, что больше нуля, требует решения до следующего заказа.
A4: Рынок | B4: Категория | C4: Месяцы с перезакупом | D4: Факт не внесён | E4: Продажи вне плана | F4: Статус
A5: =OTB!A26 | B5: =OTB!B26 | C5: =COUNTIF(OTB!D38:I38,"Перезакуп") | D5: =COUNTIF(OTB!D38:I38,"Внесите факт") | E5: =COUNTIF(OTB!D38:I38,"Продажи вне плана") | F5: =IF(SUM(C5:E5)=0,"OK","Разобрать")
A6: =OTB!A39 | B6: =OTB!B39 | C6: =COUNTIF(OTB!D51:I51,"Перезакуп") | D6: =COUNTIF(OTB!D51:I51,"Внесите факт") | E6: =COUNTIF(OTB!D51:I51,"Продажи вне плана") | F6: =IF(SUM(C6:E6)=0,"OK","Разобрать")
A7: =OTB!A52 | B7: =OTB!B52 | C7: =COUNTIF(OTB!D64:I64,"Перезакуп") | D7: =COUNTIF(OTB!D64:I64,"Внесите факт") | E7: =COUNTIF(OTB!D64:I64,"Продажи вне плана") | F7: =IF(SUM(C7:E7)=0,"OK","Разобрать")
A8: =OTB!A65 | B8: =OTB!B65 | C8: =COUNTIF(OTB!D77:I77,"Перезакуп") | D8: =COUNTIF(OTB!D77:I77,"Внесите факт") | E8: =COUNTIF(OTB!D77:I77,"Продажи вне плана") | F8: =IF(SUM(C8:E8)=0,"OK","Разобрать")
A9: Все рынки | B9: Все категории | C9: =SUM(C5:C8) | D9: =SUM(D5:D8) | E9: =SUM(E5:E8) | F9: =IF(SUM(C9:E9)=0,"OK","Разобрать")
A11: Перезакуп | B11: Open-to-buy меньше нуля: заказы и плановый остаток уже больше, чем нужно месяцу. Отмените, перенесите или разнесите заказы по месяцам.
A12: Внесите факт | B12: В закрытом месяце нет фактических продаж или поставок. План нельзя проверить, пока не внесены обе цифры.
A13: Продажи вне плана | B13: Фактические продажи отличаются от плана больше, чем на допустимое отклонение. Сначала пересчитайте прогноз на оставшиеся месяцы, потом закупайте.

Sheet Размеры и цвета
A1: Размерные и цветовые доли по очищенным продажам
A2: Берите продажи за недели, когда в наличии были все размеры: так распроданный размер не выглядит непопулярным. Закупка делится по полученным долям.
A4: Категория | B4: =OTB!B26
A5: Штук к закупке | B5: =OTB!J35
A7: Размер | B7: Очищенные продажи, шт. | C7: Доля | D7: Штук к закупке
A8: XS | B8: 90 | C8: =IF(SUM($B$8:$B$12)=0,0,B8/SUM($B$8:$B$12)) | D8: =ROUND($B$5*C8,0)
A9: S | B9: 260 | C9: =IF(SUM($B$8:$B$12)=0,0,B9/SUM($B$8:$B$12)) | D9: =ROUND($B$5*C9,0)
A10: M | B10: 340 | C10: =IF(SUM($B$8:$B$12)=0,0,B10/SUM($B$8:$B$12)) | D10: =ROUND($B$5*C10,0)
A11: L | B11: 220 | C11: =IF(SUM($B$8:$B$12)=0,0,B11/SUM($B$8:$B$12)) | D11: =ROUND($B$5*C11,0)
A12: XL | B12: 90 | C12: =IF(SUM($B$8:$B$12)=0,0,B12/SUM($B$8:$B$12)) | D12: =ROUND($B$5*C12,0)
A13: Итого | B13: =SUM(B8:B12) | C13: =SUM(C8:C12) | D13: =SUM(D8:D12)
A15: Цвет | B15: Очищенные продажи, шт. | C15: Доля | D15: Штук к закупке
A16: Чёрный | B16: 420 | C16: =IF(SUM($B$16:$B$19)=0,0,B16/SUM($B$16:$B$19)) | D16: =ROUND($B$5*C16,0)
A17: Тёмно-синий | B17: 260 | C17: =IF(SUM($B$16:$B$19)=0,0,B17/SUM($B$16:$B$19)) | D17: =ROUND($B$5*C17,0)
A18: Бежевый | B18: 190 | C18: =IF(SUM($B$16:$B$19)=0,0,B18/SUM($B$16:$B$19)) | D18: =ROUND($B$5*C18,0)
A19: Другие | B19: 130 | C19: =IF(SUM($B$16:$B$19)=0,0,B19/SUM($B$16:$B$19)) | D19: =ROUND($B$5*C19,0)
A20: Итого | B20: =SUM(B16:B19) | C20: =SUM(C16:C19) | D20: =SUM(D16:D19)
A22: После округления сумма может отличаться на одну-две штуки: поправьте самый большой размер.

Sheet Определения
A1: Определения: как и кем считается каждый показатель
A4: Показатель | B4: Как считается | C4: Кто отвечает
A5: План продаж | B5: Плановые чистые продажи месяца в розничных ценах, после возвратов, до вычета уценки. | C5: Планировщик
A6: План уценки | B6: Потери от снижения цен за месяц: полная цена минус цена продажи, умноженные на штуки, проданные со скидкой. | C6: Планировщик
A7: План остатка на конец | B7: Остаток в розничных ценах, нужный на конец месяца, обычно запас на несколько следующих недель продаж. | C7: Планировщик
A8: Остаток на начало | B8: Первый месяц: остаток на начало сезона. Следующие месяцы: плановый остаток на конец предыдущего месяца. | C8: Формула
A9: Заказано | B9: Уже размещённые заказы с поставкой в этом месяце, в розничных ценах. | C9: Байер
A10: Open-to-buy | B10: План продаж + план уценки + план остатка на конец − остаток на начало − заказано. | C10: Формула
A11: Маржинальность закупки % | B11: Плановая маржинальность новых закупок: (розничная цена − закупочная цена) ÷ розничная цена, обе без НДС. | C11: Байер и финансы
A12: Open-to-buy по себестоимости | B12: Open-to-buy × (1 − маржинальность закупки %): бюджет, который байер может потратить в закупочных ценах. | C12: Формула
A13: Средняя себестоимость единицы | B13: Средняя закупочная цена единицы новых закупок категории. | C13: Байер
A14: Open-to-buy в штуках | B14: Open-to-buy по себестоимости ÷ средняя себестоимость единицы, округлённо до целых штук. | C14: Формула
A15: Продажи и поставки факт | B15: Данные отчётов по продажам и остаткам за закрытые месяцы, в розничных ценах. | C15: Аналитик
A16: Доля размера и цвета | B16: Очищенные продажи размера или цвета ÷ очищенные продажи категории. | C16: Планировщик
